{
  "term": "Focus Buzzes",
  "categories": [
    "Technical"
  ],
  "difficultyLevel": "6",
  "pronunciation": "/ˈfoʊkəs ˈbʌzɪz/",
  "partOfSpeech": "Verb phrase",
  "englishDefinitions": [
    "Makes a buzzing sound, usually referring to the sound produced by a camera lens focusing mechanism."
  ],
  "persianTranslation": [
    "فوکوس وزوز می‌کند",
    "صدای وزوزِ فوکوس می‌دهد"
  ],
  "examples": [
    "The focus buzzes whenever the lens adjusts itself.",
    "We heard the focus buzzes during the quiet dialogue scene.",
    "If the focus buzzes too loudly, the sound team may need another take."
  ],
  "synonyms": [
    "whirs",
    "hums"
  ],
  "antonyms": []
}