{
  "term": "maraca",
  "categories": [],
  "pronunciation": "/məˈɹæ.kə/",
  "partOfSpeech": "Noun",
  "englishDefinitions": [
    "(music) A Latin American percussion instrument consisting of a hollow-gourd rattle containing pebbles or beans and often played in pairs, as a rhythm instrument.",
    "(slang, in the plural) Breasts."
  ],
  "persianTranslation": [
    "(موسیقی) یک ساز کوبه ای آمریکای لاتین متشکل از یک جغجغه توخالی کدو حاوی سنگریزه یا لوبیا است و اغلب به صورت جفت به عنوان یک ساز ریتم نواخته می شود.",
    "(عامیانه، در جمع) سینه ها."
  ],
  "examples": [],
  "synonyms": [
    "assets",
    "babylons",
    "balloons",
    "baps",
    "badonkers",
    "bangers",
    "bazongas",
    "bazookas",
    "bazoombas",
    "bazooms",
    "bewbs",
    "bobas",
    "booba",
    "boobage",
    "boobs",
    "boobers",
    "boobies",
    "boosies",
    "bosom",
    "breasts",
    "breasticles",
    "breasties",
    "bristols",
    "bubby",
    "bubs",
    "bust",
    "calcium cannons",
    "cans",
    "cantaloupes",
    "casabas",
    "charlies",
    "chebs",
    "chesticles",
    "chest melons",
    "chichis",
    "coconuts",
    "diddy",
    "ding-dongs",
    "dirty pillows",
    "double Ds",
    "dugs",
    "frontage",
    "front bumpers",
    "funbags",
    "gazongas",
    "girls",
    "globes",
    "grapefruits",
    "headlights",
    "honkers",
    "hooters",
    "itty-bittys",
    "jahoobies",
    "jigglies",
    "jubblies",
    "jugs",
    "kazooms",
    "knockers",
    "lady lumps",
    "love pillows",
    "mammaries",
    "mammary glands",
    "mammas",
    "maracas",
    "megaboobs",
    "melons",
    "milkbags",
    "milk jugs",
    "milkers",
    "mommy milkers",
    "money makers",
    "mountain [⇒ thesaurus]s",
    "norks",
    "paps",
    "pair",
    "personality",
    "puppies",
    "rack",
    "sweater puppies",
    "tatas",
    "teats",
    "tiddies",
    "tits",
    "titters",
    "titties",
    "threepenny bits",
    "top bollocks",
    "torpedos",
    "twin peaks",
    "twins",
    "udders",
    "waps",
    "watermelons",
    "yabos",
    "zoomers"
  ],
  "antonyms": []
}