{
  "categories": ["Cultural Reference", "Work & Daily Life"],
  "difficultyLevel": "8",
  "term": "Napalm",
  "pronunciation": "/ˈneɪ.pɑːm/",
  "partOfSpeech": "Noun / Verb",
  "englishDefinitions": ["A highly flammable petroleum-based substance used in incendiary bombs and flamethrowers, widely used in the Vietnam War.", "To attack a place with napalm bombs."],
  "persianTranslation": ["ناپالم (ماده آتش‌زای نظامی)", "بمب آتش‌زا", "حمله با ناپالم"],
  "examples": [
    "Napalm was used extensively during the Vietnam War and caused devastating burns.",
    "The use of napalm in civilian areas was heavily criticized by human rights organizations.",
    "Photographs from the Vietnam War showing the effects of napalm shocked the world."
  ],
  "synonyms": ["incendiary", "fire bomb", "thermite"],
  "antonyms": []
}
