{
  "term": "dust bunny",
  "categories": [],
  "pronunciation": "/ˈdʌst bʌni/",
  "partOfSpeech": "Noun",
  "englishDefinitions": [
    "(US, informal) A small clump of dust, fluff, hair, particles of skin, etc., that tends to accumulate indoors in areas not regularly dusted, such as under heavy furniture."
  ],
  "persianTranslation": [
    "(ایالات متحده، غیررسمی) توده کوچکی از گرد و غبار، کرک، مو، ذرات پوست، و غیره، که تمایل دارد در داخل خانه در مناطقی که به طور منظم گرد و غبار گرفته نمی شود، مانند زیر مبلمان سنگین، جمع شود."
  ],
  "examples": [],
  "synonyms": [
    "beggars' velvet",
    "dust kitten",
    "dust kitty",
    "dust mouse",
    "ghost turd",
    "house moss",
    "slut's wool"
  ],
  "antonyms": []
}