{
  "term": "As Though",
  "categories": [
    "Formal"
  ],
  "difficultyLevel": "4",
  "pronunciation": "/æz ðoʊ/",
  "partOfSpeech": "Conjunction",
  "englishDefinitions": [
    "used to say that something seems true or happens in a way similar to something else"
  ],
  "persianTranslation": [
    "انگار که",
    "طوری که گویی",
    "مثل اینکه"
  ],
  "examples": [
    "He looked as though he had not slept all night.",
    "She spoke as though she knew the answer already.",
    "The room felt as though time had stopped."
  ],
  "synonyms": [
    "as if"
  ],
  "antonyms": []
}