{
    "title": "The One with the Fake Monica",
    "terms": [
        {
            "id": "throw_caution_to_the_wind",
            "sources": [
                "nodir_ataev"
            ]
        },
        {
            "id": "tap",
            "sources": [
                "nodir_ataev"
            ]
        },
        {
            "id": "click",
            "sources": [
                "nodir_ataev"
            ]
        },
        {
            "id": "wait_up",
            "sources": [
                "nodir_ataev"
            ]
        }
    ]
}