{
  "term": "Mankind",
  "categories": [
    "Formal"
  ],
  "difficultyLevel": "3",
  "pronunciation": "/ˈmænˌkaɪnd/",
  "partOfSpeech": "Noun",
  "englishDefinitions": [
    "all human beings considered as a group",
    "the human race"
  ],
  "persianTranslation": [
    "بشریت",
    "نوع بشر",
    "انسانیت"
  ],
  "examples": [
    "Space exploration has always fascinated mankind.",
    "Many inventions have changed life for mankind.",
    "Scientists hope their work will benefit all mankind."
  ],
  "synonyms": [
    "humanity",
    "the human race"
  ],
  "antonyms": []
}