{
  "term": "sweat sock",
  "categories": [
    "Informal"
  ],
  "difficultyLevel": "4",
  "pronunciation": "/ˈswɛt sɑk/",
  "partOfSpeech": "Noun",
  "englishDefinitions": [
    "A sock worn for exercise or sports that helps absorb sweat and protect the foot."
  ],
  "persianTranslation": [
    "جوراب ورزشی",
    "جوراب عرق‌گیر"
  ],
  "examples": [
    "I packed extra sweat socks for the long hike.",
    "These sweat socks keep my feet dry during workouts.",
    "He changed into clean sweat socks after soccer practice."
  ],
  "synonyms": [
    "athletic sock",
    "sports sock"
  ],
  "antonyms": []
}