{
  "categories": ["Slang", "Work & Daily Life"],
  "difficultyLevel": "5",
  "term": "Hassle",
  "pronunciation": "/ˈhæs.əl/",
  "partOfSpeech": "Noun / Verb (informal)",
  "englishDefinitions": ["An annoying or troublesome situation, task, or problem.", "To persistently pester or bother someone."],
  "persianTranslation": ["دردسر", "مشکل", "اذیت کردن", "سر به سر گذاشتن"],
  "examples": [
    "Getting a visa for that country is a real hassle — the process takes weeks.",
    "Don't hassle me while I'm trying to concentrate on my work.",
    "Finding parking in the city centre is always such a hassle."
  ],
  "synonyms": ["bother", "trouble", "nuisance", "inconvenience", "annoyance"],
  "antonyms": ["ease", "convenience", "smooth sailing", "breeze"]
}
