{
  "term": "Kind Of",
  "categories": [
    "Informal",
    "Colloquial"
  ],
  "difficultyLevel": "2",
  "pronunciation": "/ˈkaɪnd əv/",
  "partOfSpeech": "Adverbial phrase",
  "englishDefinitions": [
    "Somewhat; to some degree.",
    "Used to make a statement less strong or less direct.",
    "A type or sort of something."
  ],
  "persianTranslation": [
    "تا حدی",
    "یه جورایی",
    "کمی",
    "نوعی از"
  ],
  "examples": [
    "I'm kind of tired, so I might go home early.",
    "That movie was kind of scary but also funny.",
    "What kind of music do you like?"
  ],
  "synonyms": [
    "somewhat",
    "rather",
    "a little",
    "sort of"
  ],
  "antonyms": [
    "completely",
    "totally",
    "definitely"
  ]
}