{
  "term": "Compose",
  "categories": [
    "Academic",
    "Formal"
  ],
  "difficultyLevel": "4",
  "pronunciation": "/kəmˈpoʊz/",
  "partOfSpeech": "Verb",
  "englishDefinitions": [
    "to create or write a piece of music, writing, or art",
    "to make up or form something from parts",
    "to calm oneself"
  ],
  "persianTranslation": [
    "آفریدن",
    "نوشتن/ساختن",
    "ترکیب کردن",
    "خونسرد شدن"
  ],
  "examples": [
    "He began to compose music as a teenager.",
    "The committee is composed of experts from several fields.",
    "She took a deep breath to compose herself."
  ],
  "synonyms": [
    "write",
    "create",
    "form"
  ],
  "antonyms": [
    "destroy",
    "disorganize"
  ]
}